superraenn/__init__.py
superraenn/_version.py
superraenn/classify.py
superraenn/feature_extraction.py
superraenn/lc.py
superraenn/preprocess.py
superraenn/raenn.py
superraenn/tests/__init__.py
superraenn/tests/conftest.py
superraenn/tests/running_tests.py
superraenn-1.0.4.dist-info/AUTHORS.rst
superraenn-1.0.4.dist-info/LICENSE
superraenn-1.0.4.dist-info/METADATA
superraenn-1.0.4.dist-info/WHEEL
superraenn-1.0.4.dist-info/entry_points.txt
superraenn-1.0.4.dist-info/top_level.txt
superraenn-1.0.4.dist-info/RECORD
