Metadata-Version: 2.1
Name: superraenn
Version: 1.0.4
Summary: Python package to classify  supernovae based on optical light curves
Home-page: https://github.com/villrv/superraenn
Author: V. Ashley Villar
Author-email: ashley.villar@gmail.com
License: BSD (3-clause)
Platform: UNKNOWN
Classifier: Development Status :: 2 - Pre-Alpha
Classifier: Natural Language :: English
Classifier: Programming Language :: Python :: 3
Requires-Python: >=3.7
Requires-Dist: numpy
Requires-Dist: george
Requires-Dist: scipy
Requires-Dist: astropy
Requires-Dist: recommonmark
Requires-Dist: keras
